google/cloud/monitoring_dashboard/__init__.py
google/cloud/monitoring_dashboard/gapic_version.py
google/cloud/monitoring_dashboard/py.typed
google/cloud/monitoring_dashboard_v1/__init__.py
google/cloud/monitoring_dashboard_v1/gapic_metadata.json
google/cloud/monitoring_dashboard_v1/gapic_version.py
google/cloud/monitoring_dashboard_v1/py.typed
google/cloud/monitoring_dashboard_v1/services/__init__.py
google/cloud/monitoring_dashboard_v1/services/dashboards_service/__init__.py
google/cloud/monitoring_dashboard_v1/services/dashboards_service/async_client.py
google/cloud/monitoring_dashboard_v1/services/dashboards_service/client.py
google/cloud/monitoring_dashboard_v1/services/dashboards_service/pagers.py
google/cloud/monitoring_dashboard_v1/services/dashboards_service/transports/__init__.py
google/cloud/monitoring_dashboard_v1/services/dashboards_service/transports/base.py
google/cloud/monitoring_dashboard_v1/services/dashboards_service/transports/grpc.py
google/cloud/monitoring_dashboard_v1/services/dashboards_service/transports/grpc_asyncio.py
google/cloud/monitoring_dashboard_v1/services/dashboards_service/transports/rest.py
google/cloud/monitoring_dashboard_v1/services/dashboards_service/transports/rest_base.py
google/cloud/monitoring_dashboard_v1/types/__init__.py
google/cloud/monitoring_dashboard_v1/types/alertchart.py
google/cloud/monitoring_dashboard_v1/types/collapsible_group.py
google/cloud/monitoring_dashboard_v1/types/common.py
google/cloud/monitoring_dashboard_v1/types/dashboard.py
google/cloud/monitoring_dashboard_v1/types/dashboard_filter.py
google/cloud/monitoring_dashboard_v1/types/dashboards_service.py
google/cloud/monitoring_dashboard_v1/types/drilldowns.py
google/cloud/monitoring_dashboard_v1/types/error_reporting_panel.py
google/cloud/monitoring_dashboard_v1/types/incident_list.py
google/cloud/monitoring_dashboard_v1/types/layouts.py
google/cloud/monitoring_dashboard_v1/types/logs_panel.py
google/cloud/monitoring_dashboard_v1/types/metrics.py
google_cloud_monitoring_dashboards-2.19.0.dist-info/licenses/LICENSE
google_cloud_monitoring_dashboards-2.19.0.dist-info/METADATA
google_cloud_monitoring_dashboards-2.19.0.dist-info/WHEEL
google_cloud_monitoring_dashboards-2.19.0.dist-info/top_level.txt
google_cloud_monitoring_dashboards-2.19.0.dist-info/RECORD
